{
  "id": "T-20260719-111318",
  "start_time": "2026-07-19 11:08:53",
  "end_time": "2026-07-19 11:11:42",
  "message_count": 14,
  "user_turns": 1,
  "summary": [
    {
      "from": 69,
      "to": 82,
      "topic": "价值本质讨论",
      "detail": "双方通过苏格拉底式追问达成共识：价值本质并非纯粹关系性。而是包含两层结构——基础层是现象学价值极性（痛苦本身即坏，体验内建），派生层是主体需求与客体属性的关系性拟合。这一框架同时解释了价值的规范来源和跨主体稳定性。",
      "segment_index": 0,
      "segment_count": 1,
      "range_start": "2026-07-19 11:08:53",
      "range_end": "2026-07-19 11:11:42"
    }
  ],
  "topic": "价值本质讨论",
  "detail": "双方通过苏格拉底式追问达成共识：价值本质并非纯粹关系性。而是包含两层结构——基础层是现象学价值极性（痛苦本身即坏，体验内建），派生层是主体需求与客体属性的关系性拟合。这一框架同时解释了价值的规范来源和跨主体稳定性。",
  "key_events": [
    "价值有基础体验极性和关系拟合双层。",
    "基础层价值极性是体验内建的非关系性锚点。",
    "派生层价值来自主体需求与客体属性匹配。",
    "关系论需要规范基元来解释价值的权威性。",
    "共识自洽但留有关于纯度和利他跳跃张力。"
  ],
  "topic_label": "价值本质讨论",
  "people": [
    "思源"
  ],
  "msg_indices": [
    69,
    82
  ],
  "source": "manual",
  "time_ranges": [
    [
      "2026-07-19 11:08:53",
      "2026-07-19 11:11:42"
    ]
  ],
  "range_msg_indices": [
    [
      69,
      82
    ]
  ]
}