[
  {
    "id": "C-20260711-201218",
    "source": "park_topic",
    "l1_id": "T-20260711-201203",
    "abs_from": 0,
    "abs_to": 82,
    "compressed_at": "2026-07-11 20:12:18"
  },
  {
    "id": "C-20260711-202010",
    "source": "park_topic",
    "l1_id": "T-20260711-201957",
    "abs_from": 83,
    "abs_to": 103,
    "compressed_at": "2026-07-11 20:20:10"
  },
  {
    "id": "C-20260711-202359",
    "source": "auto_summarize",
    "l1_id": "L1-20260711-202319",
    "abs_from": 104,
    "abs_to": 118,
    "compressed_at": "2026-07-11 20:23:59"
  }
]